{
  "packages": {
    "jquery-ui": {},
    "font-awesome": {},
    "moment": {},
    "iron-router": {},
    "npm": {},
    "bootstrap-datepicker": {
      "git": "https://github.com/freshjones/meteor-bootstrap-datepicker.git",
      "commit": "7c7992981969a2113d1887369e7c62a34260b5ce"
    },
    "bootstrap-3": {},
    "managedUsers": {},
    "parsleyjs": {},
    "jqbootstrapvalidation": {},
    "bootstrap-3-switch": {},
    "accounting": {},
    "crypto-md5": {},
    "crypto-aes": {},
    "crypto-sha1": {},
    "crypto-base64": {},
    "crypto-hmac": {}
  }
}
